datamodelzoo/__init__.py
datamodelzoo/__main__.py
datamodelzoo/builtin.py
datamodelzoo/case.py
datamodelzoo/constructed.py
datamodelzoo/protocol.py
datamodelzoo/special.py
datamodelzoo/stdlib.py
datamodelzoo/thirdparty.py
datamodelzoo-0.1.0.dist-info/WHEEL
datamodelzoo-0.1.0.dist-info/METADATA
datamodelzoo-0.1.0.dist-info/RECORD
